ElgatoWavePy/Mainvolume.py
ElgatoWavePy/SetMuteIn.py
ElgatoWavePy/SetMuteOut.py
ElgatoWavePy/SetOutputDevice.py
ElgatoWavePy/SetVolIn.py
ElgatoWavePy/__init__.py
ElgatoWavePy/dump.py
ElgatoWavePy/getConfig.py
ElgatoWavePy/getOutput.py
elgatowavepy-0.1.5.dist-info/licenses/LICENSE
elgatowavepy-0.1.5.dist-info/METADATA
elgatowavepy-0.1.5.dist-info/WHEEL
elgatowavepy-0.1.5.dist-info/top_level.txt
elgatowavepy-0.1.5.dist-info/RECORD
